bd_wubi/__init__.py
bd_wubi/cache.py
bd_wubi/dataset.py
bd_wubi/dictionary.py
bd_wubi/loader.py
bd_wubi/data/bd-wubi.json
bd_wubi-0.1.0.dist-info/METADATA
bd_wubi-0.1.0.dist-info/WHEEL
bd_wubi-0.1.0.dist-info/top_level.txt
bd_wubi-0.1.0.dist-info/RECORD
