Metadata-Version: 2.4
Name: bd-wubi
Version: 0.1.0
Summary: bd-wubi 数据集的 Python SDK，提供五笔查询与猜码能力。
Author: bd-wubi
Requires-Python: >=3.9
Provides-Extra: test
Requires-Dist: pytest>=8.0; extra == "test"
Provides-Extra: benchmark
